deboost/__init__.py
deboost/deboost.py
deboost-0.10.1.dist-info/METADATA
deboost-0.10.1.dist-info/WHEEL
deboost-0.10.1.dist-info/top_level.txt
deboost-0.10.1.dist-info/RECORD
